easecloud_errica/__init__.py
easecloud_errica/channels/__init__.py
easecloud_errica/channels/base.py
easecloud_errica/channels/console.py
easecloud_errica/channels/slack.py
easecloud_errica/channels/telegram.py
easecloud_errica/channels/webhook.py
easecloud_errica/core/__init__.py
easecloud_errica/core/channel_manager.py
easecloud_errica/core/config.py
easecloud_errica/core/error_handler.py
easecloud_errica/core/monitor.py
easecloud_errica/formatters/__init__.py
easecloud_errica/formatters/base.py
easecloud_errica/formatters/console.py
easecloud_errica/formatters/json.py
easecloud_errica/formatters/markdown.py
easecloud_errica/utils/__init__.py
easecloud_errica/utils/deduplicator.py
easecloud_errica/utils/rate_limiter.py
easecloud_errica-0.1.0.dist-info/METADATA
easecloud_errica-0.1.0.dist-info/WHEEL
easecloud_errica-0.1.0.dist-info/entry_points.txt
easecloud_errica-0.1.0.dist-info/top_level.txt
easecloud_errica-0.1.0.dist-info/RECORD
