Metadata-Version: 2.4
Name: easecloud-errica
Version: 0.1.0
Summary: Errica by EaseCloud Technologies — Your Python error monitor
Author-email: "EaseCloud.io" <info@easecloud.io>
License: MIT
Project-URL: Homepage, https://github.com/easecloud/easecloud-errica
Project-URL: Documentation, https://github.com/easecloud/easecloud-errica#readme
Project-URL: Repository, https://github.com/easecloud/easecloud-errica.git
Project-URL: Bug Reports, https://github.com/easecloud/easecloud-errica/issues
Project-URL: Changelog, https://github.com/easecloud/easecloud-errica/blob/main/CHANGELOG.md
Keywords: error-monitoring,logging,notifications,telegram,slack,webhook,exception-handling,multi-channel,monitoring,alerts
Classifier: Development Status :: 5 - Production/Stable
Classifier: Intended Audience :: Developers
Classifier: License :: OSI Approved :: MIT License
Classifier: Operating System :: OS Independent
Classifier: Programming Language :: Python :: 3
Classifier: Programming Language :: Python :: 3.8
Classifier: Programming Language :: Python :: 3.9
Classifier: Programming Language :: Python :: 3.10
Classifier: Programming Language :: Python :: 3.11
Classifier: Programming Language :: Python :: 3.12
Classifier: Topic :: Software Development :: Libraries :: Python Modules
Classifier: Topic :: System :: Logging
Classifier: Topic :: System :: Monitoring
Classifier: Topic :: Communications :: Chat
Classifier: Topic :: Software Development :: Quality Assurance
Classifier: Topic :: System :: Systems Administration
Requires-Python: >=3.8
Requires-Dist: requests>=2.25.0
Requires-Dist: pyyaml>=5.4.0
Provides-Extra: telegram
Requires-Dist: requests>=2.25.0; extra == "telegram"
Provides-Extra: slack
Requires-Dist: requests>=2.25.0; extra == "slack"
Provides-Extra: webhook
Requires-Dist: requests>=2.25.0; extra == "webhook"
Provides-Extra: email
Requires-Dist: smtplib; extra == "email"
Provides-Extra: socks
Requires-Dist: requests[socks]; extra == "socks"
Requires-Dist: pysocks>=1.7.0; extra == "socks"
Provides-Extra: all
Requires-Dist: requests>=2.25.0; extra == "all"
Requires-Dist: pyyaml>=5.4.0; extra == "all"
Requires-Dist: requests[socks]; extra == "all"
Requires-Dist: pysocks>=1.7.0; extra == "all"
Provides-Extra: dev
Requires-Dist: pytest>=6.0.0; extra == "dev"
Requires-Dist: pytest-asyncio>=0.18.0; extra == "dev"
Requires-Dist: pytest-cov>=2.12.0; extra == "dev"
Requires-Dist: black>=21.0.0; extra == "dev"
Requires-Dist: flake8>=3.8.0; extra == "dev"
Requires-Dist: mypy>=0.812; extra == "dev"
Requires-Dist: coverage>=5.5.0; extra == "dev"
Requires-Dist: tox>=3.20.0; extra == "dev"
Requires-Dist: pre-commit>=2.15.0; extra == "dev"
Provides-Extra: docs
Requires-Dist: sphinx>=4.0.0; extra == "docs"
Requires-Dist: sphinx-rtd-theme>=1.0.0; extra == "docs"
Requires-Dist: myst-parser>=0.15.0; extra == "docs"
